ad_mcp/__init__.py
ad_mcp-0.1.1.dist-info/METADATA
ad_mcp-0.1.1.dist-info/WHEEL
ad_mcp-0.1.1.dist-info/entry_points.txt
ad_mcp-0.1.1.dist-info/RECORD
