Metadata-Version: 2.4
Name: ad-mcp
Version: 0.1.1
Summary: Add your description here
Requires-Python: >=3.11
Requires-Dist: mcp[cli]>=1.11.0
